deephyper/__init__.py
deephyper/__version__.py
deephyper/analysis/__init__.py
deephyper/analysis/_matplotlib.py
deephyper/analysis/_rank.py
deephyper/analysis/hpo/__init__.py
deephyper/analysis/hpo/_hpo.py
deephyper/analysis/hpo/_paxplot.py
deephyper/cli/__init__.py
deephyper/cli/_cli.py
deephyper/cli/_hpo.py
deephyper/cli/utils.py
deephyper/ensemble/__init__.py
deephyper/ensemble/_ensemble.py
deephyper/ensemble/loss.py
deephyper/ensemble/aggregator/__init__.py
deephyper/ensemble/aggregator/_aggregator.py
deephyper/ensemble/aggregator/_mean.py
deephyper/ensemble/aggregator/_mixed_categorical.py
deephyper/ensemble/aggregator/_mixed_normal.py
deephyper/ensemble/aggregator/_mode.py
deephyper/ensemble/selector/__init__.py
deephyper/ensemble/selector/_greedy.py
deephyper/ensemble/selector/_online_selector.py
deephyper/ensemble/selector/_selector.py
deephyper/ensemble/selector/_topk.py
deephyper/evaluator/__init__.py
deephyper/evaluator/_decorator.py
deephyper/evaluator/_encoder.py
deephyper/evaluator/_evaluator.py
deephyper/evaluator/_job.py
deephyper/evaluator/_loky.py
deephyper/evaluator/_mpi_comm.py
deephyper/evaluator/_nest_asyncio.py
deephyper/evaluator/_process_pool.py
deephyper/evaluator/_queued.py
deephyper/evaluator/_ray.py
deephyper/evaluator/_serial.py
deephyper/evaluator/_thread_pool.py
deephyper/evaluator/callback.py
deephyper/evaluator/mpi.py
deephyper/evaluator/utils.py
deephyper/evaluator/storage/__init__.py
deephyper/evaluator/storage/_memory_storage.py
deephyper/evaluator/storage/_mpi_win_mutable_mapping.py
deephyper/evaluator/storage/_mpi_win_storage.py
deephyper/evaluator/storage/_null_storage.py
deephyper/evaluator/storage/_ray_storage.py
deephyper/evaluator/storage/_redis_storage.py
deephyper/evaluator/storage/_shared_memory_storage.py
deephyper/evaluator/storage/_storage.py
deephyper/hpo/__init__.py
deephyper/hpo/_cbo.py
deephyper/hpo/_eds.py
deephyper/hpo/_problem.py
deephyper/hpo/_random.py
deephyper/hpo/_regevo.py
deephyper/hpo/_search.py
deephyper-0.13.2.dist-info/METADATA
deephyper-0.13.2.dist-info/WHEEL
deephyper-0.13.2.dist-info/entry_points.txt
deephyper-0.13.2.dist-info/licenses/LICENSE
deephyper-0.13.2.dist-info/RECORD
