Metadata-Version: 2.4
Name: deephyper
Version: 0.13.2
Summary: Massively Parallel Hyperparameter Optimization for Machine Learning
Project-URL: Documentation, http://deephyper.readthedocs.io
Project-URL: Changes, https://github.com/deephyper/deephyper/releases
Project-URL: Forum, https://github.com/deephyper/deephyper/discussions
Project-URL: GitHub, https://github.com/deephyper/deephyper
Project-URL: Issues, https://github.com/deephyper/deephyper/issues
Author: Misha Salim, Romit Maulik, Venkat Vishwanath, Stefan Wild
Author-email: Romain Egele <regele@ornl.gov>, Prasanna Balaprakash <pbalapra@ornl.gov>
Maintainer-email: Romain Egele <regele@ornl.gov>, Prasanna Balaprakash <pbalapra@ornl.gov>
License: BSD 3-Clause License
License-File: LICENSE
Classifier: Development Status :: 3 - Alpha
Classifier: Programming Language :: Python
Classifier: Programming Language :: Python :: 3
Classifier: Programming Language :: Python :: 3.10
Classifier: Programming Language :: Python :: 3.11
Classifier: Programming Language :: Python :: 3.12
Classifier: Programming Language :: Python :: 3.13
Classifier: Programming Language :: Python :: 3.14
Requires-Python: >=3.10
Requires-Dist: cloudpickle
Requires-Dist: configspace>=1.1.1
Requires-Dist: jinja2>=3.1.4
Requires-Dist: loky>=3.4
Requires-Dist: matplotlib
Requires-Dist: numpy>=1.26.0
Requires-Dist: packaging
Requires-Dist: pandas>=0.24.2
Requires-Dist: parse
Requires-Dist: psutil
Requires-Dist: pydantic>=2.10
Requires-Dist: pymoo>=0.6.0
Requires-Dist: pyyaml
Requires-Dist: scikit-learn>=0.23.1
Requires-Dist: scipy>=1.10
Requires-Dist: tqdm>=4.64.0
Provides-Extra: core
Requires-Dist: jax[cpu]>=0.3.25; extra == 'core'
Requires-Dist: numpyro[cpu]; extra == 'core'
Requires-Dist: torch>=2.0.0; extra == 'core'
Provides-Extra: dev
Requires-Dist: build; extra == 'dev'
Requires-Dist: gitpython; extra == 'dev'
Requires-Dist: ipython; extra == 'dev'
Requires-Dist: nbsphinx; extra == 'dev'
Requires-Dist: pydata-sphinx-theme==0.15.4; extra == 'dev'
Requires-Dist: pytest; extra == 'dev'
Requires-Dist: rstcheck; extra == 'dev'
Requires-Dist: ruff; extra == 'dev'
Requires-Dist: sphinx-book-theme==1.1.4; extra == 'dev'
Requires-Dist: sphinx-copybutton; extra == 'dev'
Requires-Dist: sphinx-design==0.6.1; extra == 'dev'
Requires-Dist: sphinx-gallery; extra == 'dev'
Requires-Dist: sphinx-lfs-content; extra == 'dev'
Requires-Dist: sphinx-togglebutton; extra == 'dev'
Requires-Dist: sphinx>=5; extra == 'dev'
Requires-Dist: twine; extra == 'dev'
Provides-Extra: jax-cpu
Requires-Dist: jax[cpu]>=0.3.25; extra == 'jax-cpu'
Requires-Dist: numpyro[cpu]; extra == 'jax-cpu'
Provides-Extra: jax-cuda
Requires-Dist: jax[cuda]>=0.3.25; extra == 'jax-cuda'
Requires-Dist: numpyro[cuda]; extra == 'jax-cuda'
Provides-Extra: mpi
Requires-Dist: mpi4py>=3.1.3; extra == 'mpi'
Provides-Extra: ray
Requires-Dist: ray[default]>=1.3.0; extra == 'ray'
Provides-Extra: redis
Requires-Dist: redis; extra == 'redis'
Provides-Extra: redis-hiredis
Requires-Dist: redis[hiredis]; extra == 'redis-hiredis'
Provides-Extra: torch
Requires-Dist: torch>=2.0.0; extra == 'torch'
